{
  "2025-10-12": {
    "17758": {
      "id": 9072,
      "external_id": "17758",
      "message_preview": "VIP MARKET UPDATE: $ETH\n➖➖➖➖➖➖➖\nAfter crashing nea...h toward $4,350–$4,500.\n➖➖➖➖➖➖➖\n— Binance Killers®",
      "hash": "1edb3b2a2cc61dbf3abd96c6b7121ef7",
      "published_at": "2025-10-12 20:23:16+00:00"
    },
    "17757": {
      "id": 9075,
      "external_id": "17757",
      "message_preview": "VIP MARKET UPDATE: $BNB🔥\n➖➖➖➖➖➖➖\nAs previously sha...te short-term pullback.\n➖➖➖➖➖➖➖\n— Binance Killers®",
      "hash": "e87b24e07b697b4bc19f1b21288cc84e",
      "published_at": "2025-10-12 19:49:41+00:00"
    },
    "17755": {
      "id": 9079,
      "external_id": "17755",
      "message_preview": "VIP MARKET UPDATE: $SOL\n➖➖➖➖➖➖➖\nAs previously shar...ee retest of trendline.\n➖➖➖➖➖➖➖\n— Binance Killers®",
      "hash": "7f8d03f95a9345e1e20c23f3f16dd327",
      "published_at": "2025-10-12 19:33:16+00:00"
    },
    "17754": {
      "id": 9096,
      "external_id": "17754",
      "message_preview": "VIP MARKET UPDATE: $BTC 🔥\n➖➖➖➖➖➖➖\nPerfectly pumped...e marked support zone 🤝\n➖➖➖➖➖➖➖\n- Binance Killers®",
      "hash": "38708295f0f37dfc15713ac30111a469",
      "published_at": "2025-10-12 16:21:38+00:00"
    },
    "17753": {
      "id": 9085,
      "external_id": "17753",
      "message_preview": "$XRP 🔥...$XRP 🔥",
      "hash": "4f064297a8b14002681c1e0432be692b",
      "published_at": "2025-10-12 15:36:26+00:00"
    },
    "17752": {
      "id": 9070,
      "external_id": "17752",
      "message_preview": "VIP MARKET UPDATE: $BNB\n➖➖➖➖➖➖➖\n$BNB has shown a s...urther bullish attempt.\n➖➖➖➖➖➖➖\n— Binance Killers®",
      "hash": "e25ce35a8ae17c7a3e9c40694388f549",
      "published_at": "2025-10-12 11:29:58+00:00"
    },
    "17751": {
      "id": 9077,
      "external_id": "17751",
      "message_preview": "VIP MARKET UPDATE: $SOL\n➖➖➖➖➖➖➖\n$SOL is currently ...55 before any recovery.\n➖➖➖➖➖➖➖\n— Binance Killers®",
      "hash": "9ea74160c32df40d3a019d97877c9db4",
      "published_at": "2025-10-12 11:22:11+00:00"
    },
    "17750": {
      "id": 9084,
      "external_id": "17750",
      "message_preview": "VIP MARKET UPDATE: $XRP\n➖➖➖➖➖➖➖\nXRP is holding str... toward $2.00 or lower.\n➖➖➖➖➖➖➖\n- Binance Killers®",
      "hash": "efcdd1b3d78cd129ebbdba05c75638db",
      "published_at": "2025-10-12 09:04:51+00:00"
    },
    "17749": {
      "id": 9073,
      "external_id": "17749",
      "message_preview": "VIP MARKET UPDATE: $BTC\n➖➖➖➖➖➖➖\nA key support leve...ard move in the market.\n➖➖➖➖➖➖➖\n- Binance Killers®",
      "hash": "aa49a239ab2bdd4ffe1706bb5d767886",
      "published_at": "2025-10-12 01:15:09+00:00"
    }
  }
}