{
  "2025-08-24": {
    "9098": {
      "id": 8856,
      "external_id": "9098",
      "message_preview": "In the past 24 hours , 139,801 traders were liquid...the total liquidations comes in at $627.86 million",
      "hash": "314c418900fcb384d2255ce5e57cca94",
      "published_at": "2025-08-24 23:29:01+00:00"
    },
    "9097": {
      "id": 8849,
      "external_id": "9097",
      "message_preview": "#ETHUSDT UPDATE:\n\n#Ethereum is now currently tradi...on it and stay tuned with us for further updates✔️",
      "hash": "3b8c31cea3785390a189793f083159f1",
      "published_at": "2025-08-24 23:09:54+00:00"
    },
    "9096": {
      "id": 8847,
      "external_id": "9096",
      "message_preview": "A Bitcoin whale sold 24,000 BTC worth over $2.7 bi...till hold 152,874 BTC worth more than $17 billion.",
      "hash": "58a7143401a2d3d694ba74503934a9d9",
      "published_at": "2025-08-24 22:33:18+00:00"
    },
    "9095": {
      "id": 8861,
      "external_id": "9095",
      "message_preview": "#BTCUSDT UPDATE:\n\n#Bitcoin is currently trading ar...ee another pullback in Bitcoin. Keep an eye on it.",
      "hash": "f3b4d4e43c0e2eef9863caad7cb9f93b",
      "published_at": "2025-08-24 21:55:11+00:00"
    }
  }
}