{
  "2025-10-09": {
    "12293": {
      "id": 4726,
      "external_id": "12293",
      "message_preview": "#LRC/USDT\nSignal Type: Long \nLeverage: 5x - 25x\n\nE...0881\n0.0898\n0.0912\n0.0945\n0.0976\n\nStoploss: 0.0830",
      "hash": "dd3aa036c315244fb7422739f4049d95",
      "published_at": "2025-10-09 07:56:35+00:00"
    },
    "12292": {
      "id": 4715,
      "external_id": "12292",
      "message_preview": "Limited-Time Offer ⚠️\n\nI’m helping 5 individuals t...\n\n📩 Interested? \n\nContact admin:\n@mycsignals_admin",
      "hash": "edf2fb5b413db33a7df7120e09743f37",
      "published_at": "2025-10-09 07:46:06+00:00"
    },
    "12291": {
      "id": 4717,
      "external_id": "12291",
      "message_preview": "#ORDER/USDT\nSignal Type: Long \nLeverage: 5x - 12.5...s: \n0.325\n0.362\n0.382\n0.399\n0.410\n\nStoploss: 0.310",
      "hash": "64c2a936b8e9199401262e2fb35eb9b2",
      "published_at": "2025-10-09 07:02:04+00:00"
    }
  }
}