{
  "2025-08-12": {
    "6063": {
      "id": 5146,
      "external_id": "6063",
      "message_preview": "Premium Setup $MAVIA\n\n#MAVIA/USDT\n\nMAVIA was delis... use more than 3x Leverage.\n\nLFG 👑\n\n@CryptoSignals",
      "hash": "67a1c5bfa83a6b638672be3d79a3ff33",
      "published_at": "2025-08-12 01:22:45+00:00"
    },
    "6064": {
      "id": 5145,
      "external_id": "6064",
      "message_preview": "Mavia certainly took its time but rewards are wort...ups never fails, no matter what 💪💪\n\n@CryptoSignals",
      "hash": "24de764a4f9c43d02400611a28ea2a9e",
      "published_at": "2025-08-12 01:22:45+00:00"
    }
  }
}