{
  "2025-09-27": {
    "6095": {
      "id": 5609,
      "external_id": "6095",
      "message_preview": "⚡️⚡️⚡️⚡️\n\nhttps://x.com/CRYPTOATAL/status/19718503.../1971850346734801050?t=F5P-aeohoQKh0o44frTBzw&s=19",
      "hash": "7949aedaedb2b609445fc295e2a47089",
      "published_at": "2025-09-27 08:12:40+00:00"
    },
    "6094": {
      "id": 5602,
      "external_id": "6094",
      "message_preview": "#BTC.D\n\nIt tries to break above and find acceptanc...en get ready for Massive Altseason\n\n@cryptosignals",
      "hash": "df2e0e399105edf9e9664ad93a1d2024",
      "published_at": "2025-09-27 08:06:02+00:00"
    },
    "6093": {
      "id": 5599,
      "external_id": "6093",
      "message_preview": "#ETH\n\nEth deviated below weekly FVG and tested WOB... week but that will be bullish Dip\n\n@cryptosignals",
      "hash": "35f2c5213d4d9e39d2659a1e2e0b53c9",
      "published_at": "2025-09-27 07:51:50+00:00"
    }
  }
}