{
  "2025-09-30": {
    "2176": {
      "id": 6666,
      "external_id": "2176",
      "message_preview": "JUST IN: 🇺🇸 SEC is considering allowing stocks to ...lans to launch \"quickly,\" The Information reports.",
      "hash": "9479c7eba9884d58cc10be91c516b3b9",
      "published_at": "2025-09-30 17:40:32+00:00"
    },
    "2175": {
      "id": 6654,
      "external_id": "2175",
      "message_preview": "#WLFIUSDT UPDATE\n\nWLFI is consolidating inside a s...ing the $0.30–$0.40 zone with volume confirmation.",
      "hash": "4488522ca15a3f5e1481bb0525c061ce",
      "published_at": "2025-09-30 10:44:00+00:00"
    },
    "2174": {
      "id": 6658,
      "external_id": "2174",
      "message_preview": "#ETHUSDT  UPDATE\n\nETH is bouncing off the support ...ise, it’s just triangle yoga with no real stretch.",
      "hash": "62b889de9cccede2178299f7fc3a23da",
      "published_at": "2025-09-30 07:28:09+00:00"
    },
    "2173": {
      "id": 6661,
      "external_id": "2173",
      "message_preview": "Crypto Fear and Greed Chart.\n\nVerified Crypto Trad...o Fear and Greed Chart.\n\nVerified Crypto Traders ®",
      "hash": "08f8d39d8313808c26aefaa6f29b1b77",
      "published_at": "2025-09-30 07:27:55+00:00"
    }
  }
}