{
  "2025-08-05": {
    "1897": {
      "id": 7026,
      "external_id": "1897",
      "message_preview": "$BTC\n\nMoving in a symmetrical triangle.\n\nBreakout ...Breakout or breakdown is important to watch here 👀",
      "hash": "4ae53e80fd63dc9a4a8b79383125d2db",
      "published_at": "2025-08-05 22:26:46+00:00"
    },
    "1896": {
      "id": 7020,
      "external_id": "1896",
      "message_preview": "The crypto market right now feels like it’s on a m...re just getting caught in the middle of the chaos.",
      "hash": "8207a82f41d8c66d6d4986733b5b6af9",
      "published_at": "2025-08-05 17:07:51+00:00"
    },
    "1894": {
      "id": 7033,
      "external_id": "1894",
      "message_preview": "JUST IN: 🇨🇦 Coinbase enables PayPal integration fo...gration for Canadian users to buy and sell crypto.",
      "hash": "3bdd1a530cda5d1a7d9b91ffa4b2297b",
      "published_at": "2025-08-05 17:07:34+00:00"
    },
    "1893": {
      "id": 7021,
      "external_id": "1893",
      "message_preview": "JUST IN: 🇺🇸 White House prepares executive order t...riminate against crypto companies & conservatives.",
      "hash": "690853571144797779e54462516f86a1",
      "published_at": "2025-08-05 14:00:20+00:00"
    },
    "1892": {
      "id": 7029,
      "external_id": "1892",
      "message_preview": "#INITUSDT UPDATE\n\nINIT has broken out of the falli...g, it now appears poised for a strong upward move.",
      "hash": "e18003805f60f1e82ebc72675e5cfbb8",
      "published_at": "2025-08-05 10:17:56+00:00"
    }
  }
}