{
  "2021-05-19": {
    "449": {
      "id": 1126,
      "external_id": "449",
      "message_preview": "Tp1 ✅...Tp1 ✅",
      "hash": "aa56a7c2fcc2b96b46065c89fe5b9379",
      "published_at": "2021-05-19 16:34:51+00:00"
    },
    "448": {
      "id": 1125,
      "external_id": "448",
      "message_preview": "❌High Risk❌\n\nBinance Futures\nLONG/BUY #BTC/USDT ️ ... 44900\nLeverage: 3x\nTime: 4 days\nStop Loss:  31200",
      "hash": "210d96e81e42f2d7d04ac82f0e2a9ab0",
      "published_at": "2021-05-19 14:49:54+00:00"
    },
    "447": {
      "id": 1124,
      "external_id": "447",
      "message_preview": "I did't give you any futures signals. the last sig... some hours or maybe days for market confirmation.",
      "hash": "e9c857fe60d2f78c58f51b36dc17445a",
      "published_at": "2021-05-19 13:42:24+00:00"
    },
    "446": {
      "id": 1123,
      "external_id": "446",
      "message_preview": "we bought OGN here you had 15 minutes to buy. you ...tes to buy. you will not lose your money with me 😂",
      "hash": "89a4f839ceb6d97f8cf929778f5e65d5",
      "published_at": "2021-05-19 13:39:06+00:00"
    },
    "445": {
      "id": 1122,
      "external_id": "445",
      "message_preview": "SPOT\nMidterm 2 weeks\n\nBUY #OGN/USDT\nBuy At:  5200 ...:  5200 5000\nTP:  5400 5750 6100 6450 \nMargin 5  %",
      "hash": "ef3b85d7beba46a14bf0b3c715e0a8d2",
      "published_at": "2021-05-19 12:57:46+00:00"
    },
    "444": {
      "id": 1121,
      "external_id": "444",
      "message_preview": "#BVOL24H is reaching a sensitive area. means #BTC ...sensitive area. means #BTC trend will change soon.",
      "hash": "12e3305eedfa2dc6e0d4372783baa47b",
      "published_at": "2021-05-19 11:55:03+00:00"
    },
    "443": {
      "id": 1120,
      "external_id": "443",
      "message_preview": "#altseason index reached max value...#altseason index reached max value",
      "hash": "058d9725d622f0af9e3311165a72b6e2",
      "published_at": "2021-05-19 11:52:51+00:00"
    },
    "441": {
      "id": 1119,
      "external_id": "441",
      "message_preview": "Thanks All. I believe that you guys are best and y...ys are best and you deserve more. Thank you again.",
      "hash": "4ab84420a0976bb31ac54f12d6cbbdd0",
      "published_at": "2021-05-19 11:50:03+00:00"
    },
    "439": {
      "id": 1118,
      "external_id": "439",
      "message_preview": "Update...Update",
      "hash": "06933067aafd48425d67bcb01bba5cb6",
      "published_at": "2021-05-19 07:25:31+00:00"
    }
  }
}