{
  "2021-07-11": {
    "670": {
      "id": 1226,
      "external_id": "670",
      "message_preview": "#AXS reached entry price and it's closed. 60% prof... reached entry price and it's closed. 60% profit ✅",
      "hash": "77614f6dadb4a247d862750a3068460d",
      "published_at": "2021-07-11 22:13:44+00:00"
    },
    "664": {
      "id": 1225,
      "external_id": "664",
      "message_preview": "#DOGE smoothly going down...#DOGE smoothly going down",
      "hash": "7c3246c661b5a010150ae3c3bd5ee908",
      "published_at": "2021-07-11 08:44:14+00:00"
    }
  }
}